{
  "projectId": "eternal-card-5fs6l",
  "appId": "1:227043131357:web:a06c901e8f5d83df804034",
  "apiKey": "AIzaSyBjo3prSKDx9R8UkqBP_GQADifr7lMG8oc",
  "authDomain": "eternal-card-5fs6l.firebaseapp.com",
  "firestoreDatabaseId": "ai-studio-candia-d98c7b6b-162b-4cc3-b00a-b7d34369c1d2",
  "storageBucket": "eternal-card-5fs6l.firebasestorage.app",
  "messagingSenderId": "227043131357",
  "measurementId": "",
  "oAuthClientId": "227043131357-ldb18ie9lvu6366f7n58fdt4kndniu0i.apps.googleusercontent.com"
}